pypyrus/__init__.py
pypyrus-0.0.1.dist-info/LICENSE
pypyrus-0.0.1.dist-info/METADATA
pypyrus-0.0.1.dist-info/WHEEL
pypyrus-0.0.1.dist-info/top_level.txt
pypyrus-0.0.1.dist-info/RECORD
